{
    "collectionName": "components_skills_skills",
    "info": {
        "displayName": "skills"
    },
    "options": {},
    "attributes": {
        "name": {
            "type": "text",
            "required": true,
            "private": true,
            "unique": false
        },
        "image": {
            "allowedTypes": [
                "images",
                "files",
                "videos",
                "audios"
            ],
            "type": "media",
            "multiple": false
        }
    }
}
